gen_pop_linkml2sheets/__init__.py
gen_pop_linkml2sheets/generate_and_populate_template.py
gen_pop_linkml2sheets-0.1.9.dist-info/LICENSE.md
gen_pop_linkml2sheets-0.1.9.dist-info/METADATA
gen_pop_linkml2sheets-0.1.9.dist-info/WHEEL
gen_pop_linkml2sheets-0.1.9.dist-info/entry_points.txt
gen_pop_linkml2sheets-0.1.9.dist-info/RECORD
