Metadata-Version: 2.1
Name: gen-pop-linkml2sheets
Version: 0.1.9
Summary: 
Home-page: https://github.com/turbomam/gen-pop-linkml2sheets
License: MIT
Author: Mark Andrew Miller
Author-email: MAM@lbl.gov
Requires-Python: >=3.9,<4.0
Classifier: License :: OSI Approved :: MIT License
Classifier: Programming Language :: Python :: 3
Classifier: Programming Language :: Python :: 3.9
Classifier: Programming Language :: Python :: 3.10
Classifier: Programming Language :: Python :: 3.11
Requires-Dist: linkml (>=1.5.2,<2.0.0)
Requires-Dist: pandas (>=2.0,<3.0)
Requires-Dist: schemasheets (>=0.1.22,<0.2.0)
Project-URL: Repository, https://github.com/turbomam/gen-pop-linkml2sheets
